v_router/__init__.py
v_router/client.py
v_router/logger.py
v_router/main.py
v_router/models.yml
v_router/router.py
v_router/version.py
v_router/classes/__init__.py
v_router/classes/llm.py
v_router/classes/messages.py
v_router/classes/tools.py
v_router/providers/__init__.py
v_router/providers/anthropic.py
v_router/providers/base.py
v_router/providers/google.py
v_router/providers/openai.py
v_router-0.0.27.dist-info/METADATA
v_router-0.0.27.dist-info/WHEEL
v_router-0.0.27.dist-info/entry_points.txt
v_router-0.0.27.dist-info/RECORD
