Metadata-Version: 2.4
Name: v-router
Version: 0.0.27
Summary: A lightweight AI model router for seamlessly switching between multiple AI providers (OpenAI, Anthropic, Google AI) with unified API interface.
Author-email: Ben Selleslagh <ben@vectrix.ai>
Requires-Python: >=3.11
Requires-Dist: anthropic[vertex]>=0.52.0
Requires-Dist: colorlog>=6.9.0
Requires-Dist: google-cloud-aiplatform>=1.94.0
Requires-Dist: google-genai>=1.16.1
Requires-Dist: mammoth>=1.9.1
Requires-Dist: openai>=1.82.0
Requires-Dist: opentelemetry-instrumentation-anthropic>=0.40.9
Requires-Dist: opentelemetry-instrumentation-google-genai>=0.2b0
Requires-Dist: opentelemetry-instrumentation-openai>=0.40.9
Requires-Dist: pyyaml>=6.0.2
Provides-Extra: langfuse
Requires-Dist: langfuse>=3.0.0; extra == 'langfuse'
